
[
  {
    "image_url": "https://s2dbox.xyz/pic/movie/cover/aTo2Njc0Ow.jpg",
    "year": "2019",
    "title": "Frozen II",
    "video": "https://q11.wewon.to/a/extra/m2/2019/Frozen.2.2019.20200210.mp4?valid=rjkbkxe4sZ_5Sshj1UZRxA&t=1608226026"
  },
  {
    "image_url": "https://s2dbox.xyz/pic/movie/cover/aTo2MzU4Ow.jpg",
    "year": "2019",
    "title": "Good Boys",
    "video": "https://q11.wewon.to/a/extra/m2/2019/Good.Boys.2019.mp4?valid=hEqJIE0vdl0V_qrlMK8Pog&t=1608226385"
  },
  {
    "image_url": "https://s2dbox.xyz/pic/movie/cover/aTo2OTE2Ow.jpg",
    "year": "2019",
    "title": "Jumanji: The Next Level",
    "video": "https://q6.wewon.to/a/extra/m2/2019/Jumanji.The.Next.Level.2019.20200226.mp4?valid=B_zVeGOTHW3FKNp7jlE81g&t=1608226407"
  },
  {
    "image_url": "https://s2dbox.xyz/pic/movie/cover/aTo3MjM3Ow.jpg",
    "year": "2020",
    "title": "Trolls World Tour",
    "video": "https://q14.wewon.to/a/extra/m2/2020/Trolls.World.Tour.2020.mp4?valid=GwKp2S-L7qYNcHn0nxCrnA&t=1608226430"
  },
  {
    "image_url": "https://s2dbox.xyz/pic/movie/cover/aTo3MDQ0Ow.jpg",
    "year": "2020",
    "title": "Sonic the Hedgehog",
    "video": "https://q11.wewon.to/a/extra/m2/2020/sonic.the.hedgehog.2020.mp4?valid=wMTP7Ssb2D7zw2Q0M1ilMg&t=1608226464"
  },
  {
    "image_url": "https://s2dbox.xyz/pic/movie/cover/aTo2MjczOw.jpg",
    "year": "2019",
    "title": "It Chapter Two",
    "video": "https://q11.wewon.to/a/extra/m2/2019/It.Chapter.Two.2019.20191119.mp4?valid=802fs_GgJA1UMAZ_g0_yYg&t=1608226488"
  },
  {
    "image_url": "https://s2dbox.xyz/pic/movie/cover/aTo2MjE5Ow.jpg",
    "year": "2019",
    "title": "Spider-Man: Far from Home",
    "video": "https://q11.wewon.to/a/extra/m2/2019/Spider.Man.Far.from.Home.2019918.mp4?valid=FCFh7bS_bGyqRntOMk9Zfg&t=1608226513"
  },
  {
    "image_url": "https://s2dbox.xyz/pic/movie/cover/aTo5MDU1Ow.jpg",
    "year": "2020",
    "title": "After We Collided",
    "video": "https://q14.wewon.to/a/extra/m2/2020/After.We.Collided.2020.20201111.mp4?valid=ECaV7bGPuD2Sw5IrXEJr8Q&t=1608226533"
  },
  {
    "image_url": "https://s2dbox.xyz/pic/movie/cover/aTo3MDQzOw.jpg",
    "year": "2020",
    "title": "Birds of Prey",
    "video": "https://q6.wewon.to/a/extra/m2/2020/Birds.of.Prey.And.the.Fantabulous.Emancipation.of.One.Harley.Quinn.2020.20200321.mp4?valid=Hw_J3ZUDf3T8_CemG9ZDQw&t=1608226562"
  },
  {
    "image_url": "https://s2dbox.xyz/pic/movie/cover/aTo3MTY0Ow.jpg",
    "year": "2020",
    "title": "Bad Boys for Life",
    "video": "https://q6.wewon.to/a/extra/m2/2019/Frozen.2.2019.20200210.mp4?valid=Zl6-LQuZFBwfDvcrObGoIw&t=1608134335"
  },
  {
    "image_url": "https://s2dbox.xyz/pic/movie/cover/aToyNDM7.jpg",
    "year": "2001",
    "title": "Harry Potter and the Sorcerer's Stone",
    "video": "https://q6.wewon.to/a/extra/m1/2001/Harry.Potter.And.The.Sorcerers.Stone.200.mp4?valid=giE9mPur859wPAtvdtk3wg&t=1608226608"
  },
  {
    "image_url": "https://s2dbox.xyz/pic/movie/cover/aTo2MDk3Ow.jpg?jpg",
    "year": "2019",
    "title": "Avengers: Endgame",
    "video": "https://q14.wewon.to/a/extra/m2/2019/avengers.endgame.2019.mp4?valid=V4DwgWflA_Npt_J2mc5HpA&t=1608226632"
  },
  {
    "image_url": "https://s2dbox.xyz/pic/movie/cover/aTo3MzYxOw.jpg",
    "year": "2020",
    "title": "365 dni",
    "video": "https://q11.wewon.to/a/extra/m2/2020/365.Days.2020.mp4?valid=TIx8nZBUz8AaN5OHzR2YAA&t=1608226656"
  },
  {
    "image_url": "https://s2dbox.xyz/pic/movie/cover/aTo1MjcwOw.jpg",
    "year": "2018",
    "title": "Deadpool 2",
    "video": "https://q14.wewon.to/a/extra/m2/2018/Deadpool.2.2018.mp4?valid=66AdQHd81m_zgCwPEg-psQ&t=1608226675"
  },
  {
    "image_url": "https://s2dbox.xyz/pic/movie/cover/aTo2MjM4Ow.jpg",
    "year": "2019",
    "title": "Fast & Furious Presents: Hobbs & Shaw",
    "video": "https://q14.wewon.to/a/extra/m2/2019/Fast.and.Furious.Presents.Hobbs.and.Shaw.2019.20191019.mp4?valid=l63WJ8XSsabSR8-6S2ajFg&t=1608226695"
  },
  {
    "image_url": "https://s2dbox.xyz/pic/movie/cover/aTo2MjQ7.jpg",
    "year": "2015",
    "title": "Love",
    "video": "https://q6.wewon.to/a/extra/m1/2015/Love.2015.mp4?valid=FE-M-WLNTUQ1zlYKEmJMvA&t=1608226717"
  },
  {
    "image_url": "https://s2dbox.xyz/pic/movie/cover/aTozMzg7.jpg",
    "year": "2002",
    "title": "Harry Potter and the Chamber of Secrets",
    "video": "https://q11.wewon.to/a/extra/m1/2002/Harry.Potter.and.the.Chamber.of.Secrets.2002.mp4?valid=istC5HM7F7TQCpv2sqigYA&t=1608226741"
  },
  {
    "image_url": "https://s2dbox.xyz/pic/movie/cover/aTo3MDAwOw.jpg",
    "year": "2019",
    "title": "Spies in Disguise",
    "video": "https://q14.wewon.to/a/extra/m2/2019/Spies.in.Disguise.2019.mp4?valid=yV1AJ2NnC-gOhLwhtiWG_A&t=1608226776"
  },
  {
    "image_url": "https://s2dbox.xyz/pic/movie/cover/aTo2MjI5Ow.jpg",
    "year": "2019",
    "title": "Toy Story 4",
    "video": "https://q11.wewon.to/a/extra/m2/2019/Toy.Story.4.2019.20190915.mp4?valid=7NeU6tp8SThGYWp3ha4kSQ&t=1608226798"
  },
  {
    "image_url": "https://s2dbox.xyz/pic/movie/cover/aTozNTU7.jpg",
    "year": "2004",
    "title": "Harry Potter and the Prisoner of Azkaban",
    "video": "https://q14.wewon.to/a/extra/m2/2004/Harry.Potter.and.the.Prisoner.of.Azkaban1.2004.mp4?valid=NALcOo31XOK9UGykxiYMGw&t=1608226822"
  },
  {
    "image_url": "https://s2dbox.xyz/pic/movie/cover/aToyOTM7.jpg",
    "year": "2005",
    "title": "Harry Potter and the Goblet of Fire",
    "video": "https://q11.wewon.to/a/extra/m1/2005/Harry.Potter.and.the.Goblet.of.Fire.2005.mp4?valid=BXg-Y0PDIlmAGad9_Gle6w&t=1608226842"
  },
  {
    "image_url": "https://s2dbox.xyz/pic/movie/cover/aTo2NDc2Ow.jpg",
    "year": "2019",
    "title": "Hustlers",
    "video": "https://m4.wewon.to/a/extra/m2/2019/Hustlers.UNRATED.2019.mp4?valid=b8nIy2f4qdRBpzr4Uns0AQ&t=1608226869"
  },
  {
    "image_url": "https://s2dbox.xyz/pic/movie/cover/aTo3MTM0Ow.jpg",
    "year": "2020",
    "title": "Onward",
    "video": "https://q11.wewon.to/a/extra/m2/2020/Onward.2020.mp4?valid=kV6DIbLYcfTSRK5A5BjTiQ&t=1608226898"
  },
  {
    "image_url": "https://s2dbox.xyz/pic/movie/cover/aTo2Mjg1Ow.jpg",
    "year": "2019",
    "title": "The Lion King",
    "video": "https://q11.wewon.to/a/extra/m2/2019/Lion.King.2019.20191011.mp4?valid=DHb-wFJFtlJ92NIm6SowYw&t=1608226920"
  },
  {
    "image_url": "https://s2dbox.xyz/pic/movie/cover/aTo2MTI2Ow.jpg",
    "year": "2019",
    "title": "Aladdin",
    "video": "https://q14.wewon.to/a/extra/m2/2019/Aladdin.2019.mp4?valid=n-6ErP-2F6QYK0qYRsJa7Q&t=1608226942"
  },
  {
    "image_url": "https://s2dbox.xyz/pic/movie/cover/aTo2NjExOw.jpg",
    "year": "2019",
    "title": "The Addams Family",
    "video": "https://q14.wewon.to/a/extra/m2/2019/The.Addams.Family.2019.mp4?valid=IVm_pR8xcH1zl65i-mu7mA&t=1608226961"
  },
  {
    "image_url": "https://s2dbox.xyz/pic/movie/cover/aTo1MDUzOw.jpg",
    "year": "2017",
    "title": "Jumanji: Welcome to the Jungle",
    "video": "https://q11.wewon.to/a/extra/m1/2017/Jumanji.Welcome.to.the.Jungle.2017.mp4?valid=YX_zvg6qqZ9Zw5iAb_ZkJg&t=1608226985"
  },
  {
    "image_url": "https://s2dbox.xyz/pic/movie/cover/aTozODM7.jpg",
    "year": "2009",
    "title": "Harry Potter and the Half-Blood Prince",
    "video": "https://q11.wewon.to/a/extra/m1/2009/Harry.Potter.and.the.Half-Blood.Prince.2009.mp4?valid=H2kF9LHMNBNv0oQxrjGLZA&t=1608227009"
  },
  {
    "image_url": "https://s2dbox.xyz/pic/movie/cover/aToyOTQ7.jpg",
    "year": "2007",
    "title": "Harry Potter and the Order of the Phoenix",
    "video": "https://q6.wewon.to/a/extra/m1/2007/Harry.Potter.and.the.Order.of.the.Phoenix.2007.mp4?valid=mtG2zcQdjZTzNRqjzJziFA&t=1608227037"
  },
  {
    "image_url": "https://s2dbox.xyz/pic/movie/cover/aTo1MjYwOw.jpg",
    "year": "2018",
    "title": "Avengers: Infinity War",
    "video": "https://q11.wewon.to/a/extra/m2/2018/Avengers.Infinity.War.2018.mp4?valid=-fVLQHyW1RGC0cG9HwF1fA&t=1608227054"
  }
]
